Metadata-Version: 2.4
Name: potpyri
Version: 1.0.14.dev0
Summary: Data reduction pipeline for imaging from large aperture telescopes.
Author-email: Kerry Paterson <paterson@mpia.de>, Owen Eskandari <oeskandari@wisc.edu>, Charlie Kilpatrick <ckilpatrick@northwestern.edu>
Maintainer-email: Charlie Kilpatrick <ckilpatrick@northwestern.edu>
License:                     GNU GENERAL PUBLIC LICENSE
Project-URL: Documentation, https://CIERA-Transients.github.io/POTPyRI/
Project-URL: Source, https://github.com/CIERA-Transients/POTPyRI
Classifier: Development Status :: 1 - Planning
Classifier: Topic :: Scientific/Engineering :: Astronomy
Classifier: License :: OSI Approved :: MIT License
Classifier: Programming Language :: Python :: 3.12
Classifier: Programming Language :: Python :: 3.11
Classifier: Programming Language :: Python :: 3 :: Only
Requires-Python: >=3.11.0
License-File: LICENSE.txt
Requires-Dist: acstools
Requires-Dist: astropy
Requires-Dist: astroquery
Requires-Dist: beautifulsoup4
Requires-Dist: ccdproc
Requires-Dist: gdown
Requires-Dist: matplotlib
Requires-Dist: numpy
Requires-Dist: photutils
Requires-Dist: progressbar
Requires-Dist: pykoa
Requires-Dist: requests
Requires-Dist: scipy
Provides-Extra: test
Requires-Dist: pytest; extra == "test"
Requires-Dist: pytest-cov; extra == "test"
Requires-Dist: requests; extra == "test"
Provides-Extra: docs
Requires-Dist: sphinx==8.1.3; extra == "docs"
Requires-Dist: nbsphinx; extra == "docs"
Requires-Dist: sphinx-astropy; extra == "docs"
Requires-Dist: pandoc; extra == "docs"
Requires-Dist: sphinx-multiversion; extra == "docs"
Requires-Dist: sphinxawesome-theme; extra == "docs"
Dynamic: license-file
